{"nodes": [{"id": "signature_help", "label": "signature-help.ts", "file_type": "code", "source_file": "packages\\tooling\\language-server\\src\\handlers\\signature-help.ts", "source_location": "L1"}, {"id": "signature_help_setupsignaturehelphandler", "label": "setupSignatureHelpHandler()", "file_type": "code", "source_file": "packages\\tooling\\language-server\\src\\handlers\\signature-help.ts", "source_location": "L13"}], "edges": [{"source": "signature_help", "target": "node", "relation": "imports_from", "confidence": "EXTRACTED", "source_file": "packages\\tooling\\language-server\\src\\handlers\\signature-help.ts", "source_location": "L1", "weight": 1.0}, {"source": "signature_help", "target": "vscode_languageserver_textdocument", "relation": "imports_from", "confidence": "EXTRACTED", "source_file": "packages\\tooling\\language-server\\src\\handlers\\signature-help.ts", "source_location": "L9", "weight": 1.0}, {"source": "signature_help", "target": "index", "relation": "imports_from", "confidence": "EXTRACTED", "source_file": "packages\\tooling\\language-server\\src\\handlers\\signature-help.ts", "source_location": "L10", "weight": 1.0}, {"source": "signature_help", "target": "settings", "relation": "imports_from", "confidence": "EXTRACTED", "source_file": "packages\\tooling\\language-server\\src\\handlers\\signature-help.ts", "source_location": "L11", "weight": 1.0}, {"source": "signature_help", "target": "signature_help_setupsignaturehelphandler", "relation": "contains", "confidence": "EXTRACTED", "source_file": "packages\\tooling\\language-server\\src\\handlers\\signature-help.ts", "source_location": "L13", "weight": 1.0}]}