{"nodes": [{"id": "route_manager", "label": "route-manager.ts", "file_type": "code", "source_file": "packages\\core\\scene\\src\\route-manager.ts", "source_location": "L1"}, {"id": "route_manager_routemanager", "label": "RouteManager", "file_type": "code", "source_file": "packages\\core\\scene\\src\\route-manager.ts", "source_location": "L5"}, {"id": "route_manager_routemanager_register", "label": ".register()", "file_type": "code", "source_file": "packages\\core\\scene\\src\\route-manager.ts", "source_location": "L13"}, {"id": "route_manager_routemanager_validaterouteinputs", "label": ".validateRouteInputs()", "file_type": "code", "source_file": "packages\\core\\scene\\src\\route-manager.ts", "source_location": "L30"}, {"id": "route_manager_routemanager_match", "label": ".match()", "file_type": "code", "source_file": "packages\\core\\scene\\src\\route-manager.ts", "source_location": "L47"}, {"id": "route_manager_routemanager_trymatchroute", "label": ".tryMatchRoute()", "file_type": "code", "source_file": "packages\\core\\scene\\src\\route-manager.ts", "source_location": "L68"}, {"id": "route_manager_routemanager_extractparams", "label": ".extractParams()", "file_type": "code", "source_file": "packages\\core\\scene\\src\\route-manager.ts", "source_location": "L90"}, {"id": "route_manager_routemanager_parsepath", "label": ".parsePath()", "file_type": "code", "source_file": "packages\\core\\scene\\src\\route-manager.ts", "source_location": "L102"}, {"id": "route_manager_routemanager_clear", "label": ".clear()", "file_type": "code", "source_file": "packages\\core\\scene\\src\\route-manager.ts", "source_location": "L123"}], "edges": [{"source": "route_manager", "target": "constants", "relation": "imports_from", "confidence": "EXTRACTED", "source_file": "packages\\core\\scene\\src\\route-manager.ts", "source_location": "L1", "weight": 1.0}, {"source": "route_manager", "target": "types", "relation": "imports_from", "confidence": "EXTRACTED", "source_file": "packages\\core\\scene\\src\\route-manager.ts", "source_location": "L2", "weight": 1.0}, {"source": "route_manager", "target": "utils", "relation": "imports_from", "confidence": "EXTRACTED", "source_file": "packages\\core\\scene\\src\\route-manager.ts", "source_location": "L3", "weight": 1.0}, {"source": "route_manager", "target": "route_manager_routemanager", "relation": "contains", "confidence": "EXTRACTED", "source_file": "packages\\core\\scene\\src\\route-manager.ts", "source_location": "L5", "weight": 1.0}, {"source": "route_manager_routemanager", "target": "route_manager_routemanager_register", "relation": "method", "confidence": "EXTRACTED", "source_file": "packages\\core\\scene\\src\\route-manager.ts", "source_location": "L13", "weight": 1.0}, {"source": "route_manager_routemanager", "target": "route_manager_routemanager_validaterouteinputs", "relation": "method", "confidence": "EXTRACTED", "source_file": "packages\\core\\scene\\src\\route-manager.ts", "source_location": "L30", "weight": 1.0}, {"source": "route_manager_routemanager", "target": "route_manager_routemanager_match", "relation": "method", "confidence": "EXTRACTED", "source_file": "packages\\core\\scene\\src\\route-manager.ts", "source_location": "L47", "weight": 1.0}, {"source": "route_manager_routemanager", "target": "route_manager_routemanager_trymatchroute", "relation": "method", "confidence": "EXTRACTED", "source_file": "packages\\core\\scene\\src\\route-manager.ts", "source_location": "L68", "weight": 1.0}, {"source": "route_manager_routemanager", "target": "route_manager_routemanager_extractparams", "relation": "method", "confidence": "EXTRACTED", "source_file": "packages\\core\\scene\\src\\route-manager.ts", "source_location": "L90", "weight": 1.0}, {"source": "route_manager_routemanager", "target": "route_manager_routemanager_parsepath", "relation": "method", "confidence": "EXTRACTED", "source_file": "packages\\core\\scene\\src\\route-manager.ts", "source_location": "L102", "weight": 1.0}, {"source": "route_manager_routemanager", "target": "route_manager_routemanager_clear", "relation": "method", "confidence": "EXTRACTED", "source_file": "packages\\core\\scene\\src\\route-manager.ts", "source_location": "L123", "weight": 1.0}, {"source": "route_manager_routemanager_register", "target": "route_manager_routemanager_validaterouteinputs", "relation": "calls", "confidence": "EXTRACTED", "source_file": "packages\\core\\scene\\src\\route-manager.ts", "source_location": "L14", "weight": 1.0}, {"source": "route_manager_routemanager_register", "target": "route_manager_routemanager_parsepath", "relation": "calls", "confidence": "EXTRACTED", "source_file": "packages\\core\\scene\\src\\route-manager.ts", "source_location": "L18", "weight": 1.0}, {"source": "route_manager_routemanager_match", "target": "route_manager_routemanager_trymatchroute", "relation": "calls", "confidence": "EXTRACTED", "source_file": "packages\\core\\scene\\src\\route-manager.ts", "source_location": "L56", "weight": 1.0}, {"source": "route_manager_routemanager_trymatchroute", "target": "route_manager_routemanager_extractparams", "relation": "calls", "confidence": "EXTRACTED", "source_file": "packages\\core\\scene\\src\\route-manager.ts", "source_location": "L80", "weight": 1.0}]}